BMIfindtest/find.py
BMIfindtest-0.0.0.2.dist-info/METADATA
BMIfindtest-0.0.0.2.dist-info/WHEEL
BMIfindtest-0.0.0.2.dist-info/top_level.txt
BMIfindtest-0.0.0.2.dist-info/RECORD
